mensurapy/__init__.py
mensurapy/area.py
mensurapy/calculate_area.py
mensurapy/calculate_perimeter.py
mensurapy/calculate_surface_area.py
mensurapy/calculate_volume.py
mensurapy/param_parser_area.py
mensurapy/param_parser_perimeter.py
mensurapy/param_parser_surface_area.py
mensurapy/param_parser_volume.py
mensurapy/param_validator_area.py
mensurapy/param_validator_perimeter.py
mensurapy/param_validator_surface_area.py
mensurapy/param_validator_volume.py
mensurapy/perimeter.py
mensurapy/surface_area.py
mensurapy/unit_converter.py
mensurapy/volume.py
mensurapy-0.2.0.dist-info/licenses/LICENSE.txt
tests/__init__.py
tests/test_area.py
tests/test_perimeter.py
tests/test_surface_area.py
tests/test_volume.py
mensurapy-0.2.0.dist-info/METADATA
mensurapy-0.2.0.dist-info/WHEEL
mensurapy-0.2.0.dist-info/top_level.txt
mensurapy-0.2.0.dist-info/RECORD
