Metadata-Version: 2.4
Name: mensurapy
Version: 0.2.0
Summary: MensuraPy is a Python package that provides accurate and user-friendly functions to calculate the area, perimeter, surface area, and volume of 2D and 3D geometric shapes.
Home-page: https://github.com/Anuva13/MensuraPy.git
Author: Anuva Das
Author-email: Anuva13 <anuvadas@hotmail.com>
Maintainer-email: Anuva13 <anuvadas@hotmail.com>
License: MIT
Project-URL: Homepage, https://github.com/Anuva13/MensuraPy
Project-URL: Documentation, https://github.com/Anuva13/MensuraPy/tree/main/MensuraPy
Project-URL: Bug Tracker, https://github.com/Anuva13/MensuraPy/issues
Project-URL: Security, https://github.com/Anuva13/MensuraPy/security
Project-URL: Source, https://github.com/Anuva13/MensuraPy
Keywords: geometry,mensuration,area,volume,perimeter,surface-area,math,shapes
Classifier: Development Status :: 4 - Beta
Classifier: License :: OSI Approved :: MIT License
Classifier: Intended Audience :: Developers
Classifier: Intended Audience :: Education
Classifier: Programming Language :: Python
Classifier: Programming Language :: Python :: 3
Classifier: Programming Language :: Python :: 3.7
Classifier: Programming Language :: Python :: 3.8
Classifier: Programming Language :: Python :: 3.9
Classifier: Programming Language :: Python :: 3.10
Classifier: Programming Language :: Python :: 3.11
Classifier: Programming Language :: Python :: 3.12
Classifier: Topic :: Education
Classifier: Topic :: Scientific/Engineering :: Mathematics
Requires-Python: >=3.7
License-File: LICENSE.txt
Dynamic: author
Dynamic: home-page
Dynamic: license-file
